streamsx/toolkits/__init__.py
streamsx/toolkits/_toolkits.py
streamsx.toolkits-1.3.1.dist-info/DESCRIPTION.rst
streamsx.toolkits-1.3.1.dist-info/LICENSE.txt
streamsx.toolkits-1.3.1.dist-info/METADATA
streamsx.toolkits-1.3.1.dist-info/RECORD
streamsx.toolkits-1.3.1.dist-info/WHEEL
streamsx.toolkits-1.3.1.dist-info/metadata.json
streamsx.toolkits-1.3.1.dist-info/top_level.txt
